pvextractor/__init__.py
pvextractor/conftest.py
pvextractor/gui.py
pvextractor/pvextractor.py
pvextractor/pvregions.py
pvextractor/version.py
pvextractor/geometry/__init__.py
pvextractor/geometry/helpers.py
pvextractor/geometry/line_slices.py
pvextractor/geometry/path.py
pvextractor/geometry/poly_slices.py
pvextractor/geometry/polygon.py
pvextractor/geometry/slices.py
pvextractor/geometry/tests/__init__.py
pvextractor/geometry/tests/test_helpers.py
pvextractor/tests/__init__.py
pvextractor/tests/setup_package.py
pvextractor/tests/test_gui.py
pvextractor/tests/test_path.py
pvextractor/tests/test_slicer.py
pvextractor/tests/test_wcspath.py
pvextractor/tests/data/tests.reg
pvextractor/tests/data/w51.hdr
pvextractor/utils/__init__.py
pvextractor/utils/wcs_slicing.py
pvextractor/utils/wcs_utils.py
pvextractor-0.4.dist-info/LICENSE
pvextractor-0.4.dist-info/METADATA
pvextractor-0.4.dist-info/WHEEL
pvextractor-0.4.dist-info/top_level.txt
pvextractor-0.4.dist-info/RECORD
