Metadata-Version: 2.1
Name: pvextractor
Version: 0.4
Summary: Position-velocity diagram extractor.
Home-page: http://pvextractor.readthedocs.io
Author: Adam Ginsburg and Thomas Robitaille
Author-email: adam.g.ginsburg@gmail.com
License: BSD 3-Clause
Requires-Python: >=3.8
License-File: LICENSE
Requires-Dist: numpy>=1.22
Requires-Dist: astropy>=5.0
Requires-Dist: matplotlib>=3.5
Requires-Dist: scipy>=1.8
Requires-Dist: qtpy>=2.0
Requires-Dist: spectral-cube>=0.4
Provides-Extra: test
Requires-Dist: pytest-astropy; extra == "test"
Provides-Extra: docs
Requires-Dist: sphinx-astropy; extra == "docs"
